brickastley/__init__.py
brickastley/apps.py
brickastley/autodiscover.py
brickastley/brick.py
brickastley/registry.py
brickastley/templatetags/__init__.py
brickastley/templatetags/brickastley.py
django_brick_astley-0.4.0.dist-info/licenses/LICENSE
django_brick_astley-0.4.0.dist-info/METADATA
django_brick_astley-0.4.0.dist-info/WHEEL
django_brick_astley-0.4.0.dist-info/top_level.txt
django_brick_astley-0.4.0.dist-info/RECORD
